LICENSE
README.md
setup.py
eospyabi/__init__.py
eospyabi/__version__.py
eospyabi/cleos.py
eospyabi/command_line.py
eospyabi/dynamic_url.py
eospyabi/exceptions.py
eospyabi/keys.py
eospyabi/schema.py
eospyabi/signer.py
eospyabi/testeos.py
eospyabi/types.py
eospyabi/utils.py
eospyabi.egg-info/PKG-INFO
eospyabi.egg-info/SOURCES.txt
eospyabi.egg-info/dependency_links.txt
eospyabi.egg-info/entry_points.txt
eospyabi.egg-info/requires.txt
eospyabi.egg-info/top_level.txt
tests/test_cleos.py
tests/test_sig.py