Metadata-Version: 2.1
Name: eospyabi
Version: 0.2.0
Summary: Python library for the eos.io REST API
Home-page: https://github.com/MajicGit/eospyABI
Author: MajicGit
License-File: LICENSE
Requires-Dist: requests
Requires-Dist: base58>=1.0.3
Requires-Dist: ecdsa
Requires-Dist: colander
Requires-Dist: pytz
Requires-Dist: six
Requires-Dist: pyyaml
Requires-Dist: antelopy==0.2.0
